tiny_spidey
