Metadata-Version: 1.0
Name: tiny-spidey
Version: 1.1
Summary: A really basic web crawler.
Home-page: https://github.com/simpko/tiny_spidey
Author: Joonho Ko
Author-email: joonhok@mit.edu
License: MIT
Platform: UNKNOWN
